pkgpy/__init__.py
pkgpy-0.3.dist-info/LICENSE
pkgpy-0.3.dist-info/METADATA
pkgpy-0.3.dist-info/WHEEL
pkgpy-0.3.dist-info/top_level.txt
pkgpy-0.3.dist-info/RECORD
