Metadata-Version: 2.1
Name: pkgpy
Version: 0.3
Summary: pkgpy
Home-page: http://github.com/eris9/pkgpy
Author: Eris9/Sakurai07
Author-email: blzzardst0rm@gmail.com
License: MIT
Platform: UNKNOWN
